explorer/__init__.py
explorer/explorer.py
explorer/configs/GOERLI-stable.json
explorer/configs/KOVAN-stable.json
explorer/configs/MAIN-stable.json
explorer/configs/RINKEBY-stable.json
explorer/configs/ROPSTEN-stable.json
explorer/configs/__init__.py
explorer/enums/__init__.py
explorer/enums/actions_enum.py
explorer/enums/fields_enum.py
explorer/enums/modules_enum.py
explorer/enums/tags_enum.py
explorer/modules/__init__.py
explorer/modules/accounts.py
explorer/modules/blocks.py
explorer/modules/contracts.py
explorer/modules/gastracker.py
explorer/modules/pro.py
explorer/modules/proxy.py
explorer/modules/stats.py
explorer/modules/tokens.py
explorer/modules/transactions.py
explorer/utils/__init__.py
explorer/utils/conversions.py
explorer/utils/parsing.py
anyscan-1.0.0.dist-info/LICENSE
anyscan-1.0.0.dist-info/METADATA
anyscan-1.0.0.dist-info/WHEEL
anyscan-1.0.0.dist-info/top_level.txt
anyscan-1.0.0.dist-info/RECORD
