Metadata-Version: 2.1
Name: anyscan
Version: 1.0.0
Summary: A minimal, yet complete, python API for any block explorer powered by the Etherscan team. (e.g. etherscan.io, arbiscan.io, polygonscan.com, ...
Home-page: https://github.com/gerrrg/anyscan
Author: gerrrg
License: MIT
License-File: LICENSE
Requires-Dist: requests
